api_fhir/__init__.py
api_fhir/admin.py
api_fhir/apps.py
api_fhir/paginations.py
api_fhir/permissions.py
api_fhir/urls.py
api_fhir/views.py
api_fhir/configurations/__init__.py
api_fhir/configurations/generalConfiguration.py
api_fhir/configurations/moduleConfiguration.py
api_fhir/configurations/stu3ApiFhirConfig.py
api_fhir/configurations/stu3ClaimConfig.py
api_fhir/configurations/stu3CommunicationRequestConfig.py
api_fhir/configurations/stu3CoverageConfig.py
api_fhir/configurations/stu3EligibilityConfiguration.py
api_fhir/configurations/stu3IdentifierConfig.py
api_fhir/configurations/stu3IssueTypeConfig.py
api_fhir/configurations/stu3LocationConfig.py
api_fhir/configurations/stu3MaritalConfig.py
api_fhir/converters/__init__.py
api_fhir/converters/claimConverter.py
api_fhir/converters/claimResponseConverter.py
api_fhir/converters/communicationRequestConverter.py
api_fhir/converters/contractConverter.py
api_fhir/converters/coverageConventer.py
api_fhir/converters/eligibilityRequestConverter.py
api_fhir/converters/locationConverter.py
api_fhir/converters/operationOutcomeConverter.py
api_fhir/converters/patientConverter.py
api_fhir/converters/personConverterMixin.py
api_fhir/converters/policyEligibilityRequestConverter.py
api_fhir/converters/practitionerConverter.py
api_fhir/converters/practitionerRoleConverter.py
api_fhir/converters/referenceConverterMixin.py
api_fhir/exceptions/__init__.py
api_fhir/exceptions/fhir_api_exception_handler.py
api_fhir/migrations/__init__.py
api_fhir/models/__init__.py
api_fhir/models/address.py
api_fhir/models/administrative.py
api_fhir/models/age.py
api_fhir/models/annotation.py
api_fhir/models/attachment.py
api_fhir/models/backboneElement.py
api_fhir/models/bundle.py
api_fhir/models/claim.py
api_fhir/models/claimResponse.py
api_fhir/models/codeableConcept.py
api_fhir/models/coding.py
api_fhir/models/communicationRequest.py
api_fhir/models/contactPoint.py
api_fhir/models/contract.py
api_fhir/models/count.py
api_fhir/models/coverage.py
openimis_be_api_fhir-1.1.0.dist-info/LICENSE.md
openimis_be_api_fhir-1.1.0.dist-info/METADATA
openimis_be_api_fhir-1.1.0.dist-info/WHEEL
openimis_be_api_fhir-1.1.0.dist-info/top_level.txt
openimis_be_api_fhir-1.1.0.dist-info/RECORD
