Metadata-Version: 2.1
Name: openimis-be-api-fhir
Version: 1.1.0
Summary: The openIMIS Backend FHIR API reference module.
Home-page: https://openimis.org/
Author: Arkadiusz Lalo
Author-email: alalo@soldevelo.com
License: GNU AGPL v3
Platform: UNKNOWN
Classifier: Environment :: Web Environment
Classifier: Framework :: Django
Classifier: Framework :: Django :: 2.1
Classifier: Intended Audience :: Developers
Classifier: License :: OSI Approved :: GNU Affero General Public License v3
Classifier: Operating System :: OS Independent
Classifier: Programming Language :: Python
Classifier: Programming Language :: Python :: 3.5
Classifier: Programming Language :: Python :: 3.6
Classifier: Programming Language :: Python :: 3.7
Requires-Dist: django
Requires-Dist: django-db-signals
Requires-Dist: djangorestframework
Requires-Dist: openimis-be-claim
Requires-Dist: openimis-be-core
Requires-Dist: openimis-be-insuree
Requires-Dist: openimis-be-location
Requires-Dist: openimis-be-policy
